{
	"configurations" : 
	[
		{
			"directories" : 
			[
				{
					"build" : ".",
					"jsonFile" : "directory-.-Debug-d0094a50bb2071803777.json",
					"minimumCMakeVersion" : 
					{
						"string" : "3.26"
					},
					"projectIndex" : 0,
					"source" : ".",
					"targetIndexes" : 
					[
						0
					]
				}
			],
			"name" : "Debug",
			"projects" : 
			[
				{
					"directoryIndexes" : 
					[
						0
					],
					"name" : "domashno6",
					"targetIndexes" : 
					[
						0
					]
				}
			],
			"targets" : 
			[
				{
					"directoryIndex" : 0,
					"id" : "domashno6::@6890427a1f51a3e7e1df",
					"jsonFile" : "target-domashno6-Debug-f36a958e900ae70e4952.json",
					"name" : "domashno6",
					"projectIndex" : 0
				}
			]
		}
	],
	"kind" : "codemodel",
	"paths" : 
	{
		"build" : "C:/Users/Dari/Desktop/IS/domashno6/cmake-build-debug",
		"source" : "C:/Users/Dari/Desktop/IS/domashno6"
	},
	"version" : 
	{
		"major" : 2,
		"minor" : 5
	}
}
